[{"id":1993,"title":"Radiant VII","year":2197},{"id":1994,"title":"Azure Angel II","year":2185},{"id":1995,"title":"Invisible Hand","year":2689},{"id":1996,"title":"Invisible Hand","year":2241},{"id":1997,"title":"Scimitar","year":2420},{"id":1998,"title":"Ebon Hawk","year":2927},{"id":1999,"title":"Outrider","year":2406},{"id":2000,"title":"Outrider","year":2689},{"id":2001,"title":"Invisible Hand","year":2597},{"id":2002,"title":"Slave I","year":2756},{"id":2003,"title":"Death Star","year":2175},{"id":2004,"title":"Radiant VII","year":2946},{"id":2005,"title":"Rogue Shadow","year":2469},{"id":2006,"title":"Tantive IV","year":2825},{"id":2007,"title":"Ebon Hawk","year":2333},{"id":2008,"title":"Tantive IV","year":2818},{"id":2009,"title":"Radiant VII","year":2499},{"id":2010,"title":"Raven's Claw","year":2840},{"id":2011,"title":"Virago","year":2440},{"id":2012,"title":"Tantive IV","year":2635}]