[{"id":238,"title":"Azure Angel II","year":2967},{"id":239,"title":"Slave I","year":2657},{"id":240,"title":"Soulless One","year":2638},{"id":241,"title":"Azure Angel II","year":2152},{"id":242,"title":"Ebon Hawk","year":2684},{"id":243,"title":"Raven's Claw","year":2249},{"id":244,"title":"Moldy Crow","year":2979},{"id":245,"title":"Ebon Hawk","year":2775},{"id":246,"title":"Virago","year":2780},{"id":247,"title":"Tantive IV","year":2148},{"id":248,"title":"Soulless One","year":2352},{"id":249,"title":"Saak'ak","year":2110},{"id":250,"title":"Soulless One","year":2454},{"id":251,"title":"Soulless One","year":2816},{"id":252,"title":"Death Star","year":2727},{"id":253,"title":"Invisible Hand","year":2753},{"id":254,"title":"Tantive IV","year":2692},{"id":255,"title":"Ebon Hawk","year":2801},{"id":256,"title":"Saak'ak","year":2448},{"id":257,"title":"Moldy Crow","year":2900}]