[{"id":347,"title":"Saak'ak","year":2496},{"id":348,"title":"Moldy Crow","year":2707},{"id":349,"title":"Death Star","year":2895},{"id":350,"title":"Slave I","year":2777},{"id":351,"title":"Radiant VII","year":2532},{"id":352,"title":"Azure Angel II","year":2703},{"id":353,"title":"Azure Angel II","year":2321},{"id":354,"title":"Outrider","year":2860},{"id":355,"title":"Tantive IV","year":2513},{"id":356,"title":"Virago","year":2714},{"id":357,"title":"Death Star","year":2202},{"id":358,"title":"Virago","year":2370},{"id":359,"title":"Scimitar","year":2220},{"id":360,"title":"Moldy Crow","year":2294},{"id":361,"title":"Ebon Hawk","year":2540},{"id":362,"title":"Tantive IV","year":2379},{"id":363,"title":"Azure Angel II","year":2976},{"id":364,"title":"Rogue Shadow","year":2073},{"id":365,"title":"Scimitar","year":2710},{"id":366,"title":"Rogue Shadow","year":2228}]