[{"id":688,"title":"Outrider","year":2232},{"id":689,"title":"Scimitar","year":2755},{"id":690,"title":"Tantive IV","year":2714},{"id":691,"title":"Radiant VII","year":2866},{"id":692,"title":"Death Star","year":2691},{"id":693,"title":"Death Star","year":2115},{"id":694,"title":"Ghost","year":2382},{"id":695,"title":"Scimitar","year":2641},{"id":696,"title":"Rogue Shadow","year":2794},{"id":697,"title":"Azure Angel II","year":2432},{"id":698,"title":"Slave I","year":2052},{"id":699,"title":"Saak'ak","year":2997},{"id":700,"title":"Soulless One","year":2253},{"id":701,"title":"Azure Angel II","year":2125},{"id":702,"title":"Millennium Falcon","year":2682},{"id":703,"title":"Death Star","year":2866},{"id":704,"title":"Radiant VII","year":2252},{"id":705,"title":"Rogue Shadow","year":2173},{"id":706,"title":"Slave I","year":2791},{"id":707,"title":"Azure Angel II","year":2754}]